simple_qiwi/Errors.py
simple_qiwi/Session.py
simple_qiwi/Webhook.py
simple_qiwi/__init__.py
simple_qiwi-0.8.dist-info/LICENSE.md
simple_qiwi-0.8.dist-info/METADATA
simple_qiwi-0.8.dist-info/WHEEL
simple_qiwi-0.8.dist-info/top_level.txt
simple_qiwi-0.8.dist-info/RECORD
