Metadata-Version: 2.1
Name: simple-qiwi
Version: 0.8
Summary: QIWI API for Humans
Home-page: https://github.com/protectedsnow/simple_qiwi
Author: protectedsnow
Author-email: UNKNOWN
License: UNKNOWN
Platform: UNKNOWN
Requires-Dist: requests
Requires-Dist: uuid
Requires-Dist: flask
